src/__init__.py
src/alpha/__init__.py
src/alpha/base_alpha.py
src/alpha/intraday_alpha.py
src/alpha/overnight_alpha.py
src/alpha/trading_alpha.py
src/models/__init__.py
src/models/afs_model.py
src/models/impact_model.py
src/models/ow_model.py
src/schedule/__init__.py
src/schedule/schedule.py
src/tca/__init__.py
src/tca/tca_report.py
testing/__init__.py
testing/test_cfg.py
impactpy_lachlanbaxter-0.0.1.dist-info/METADATA
impactpy_lachlanbaxter-0.0.1.dist-info/WHEEL
impactpy_lachlanbaxter-0.0.1.dist-info/top_level.txt
impactpy_lachlanbaxter-0.0.1.dist-info/RECORD
